rcon_mcp/__init__.py
rcon_mcp/__main__.py
rcon_mcp/commands.py
rcon_mcp/config.py
rcon_mcp/server.py
rcon_mcp/utils.py
mseep_rcon_mcp-0.1.5.dist-info/METADATA
mseep_rcon_mcp-0.1.5.dist-info/WHEEL
mseep_rcon_mcp-0.1.5.dist-info/entry_points.txt
mseep_rcon_mcp-0.1.5.dist-info/licenses/LICENSE
mseep_rcon_mcp-0.1.5.dist-info/RECORD
