Metadata-Version: 2.4
Name: mseep-rcon-mcp
Version: 0.1.5
Summary: A Model Context Protocol server for CS2 RCON management
Author-email: mseep <support@skydeck.ai>
License-File: LICENSE
Requires-Python: >=3.8
Requires-Dist: mcp==1.3.0
Requires-Dist: python-dotenv==1.0.1
Requires-Dist: rcon
Requires-Dist: sse-starlette==2.2.1
Requires-Dist: starlette==0.46.0
Requires-Dist: uvicorn==0.34.0
